MANIFEST.in
README.md
setup.py
py_tree/__init__.py
py_tree/__main__.py
py_tree/command_line.py
py_tree/directory_explorer.py
py_tree/directory_tree.py
py_tree/tree_printer.py
py_tree.egg-info/PKG-INFO
py_tree.egg-info/SOURCES.txt
py_tree.egg-info/dependency_links.txt
py_tree.egg-info/entry_points.txt
py_tree.egg-info/not-zip-safe
py_tree.egg-info/top_level.txt