Metadata-Version: 1.1
Name: py-tree
Version: 1.0.0
Summary: Text-based graphcial representation of file hierarchies
Home-page: http://github.com/tdeh/py-tree
Author: Taylor DeHaan
Author-email: tdehaan93@gmail.com
License: Apache
Keywords: tree directory files hierarchy
Platform: UNKNOWN
Classifier: Development Status :: 3 - Alpha
Classifier: Environment :: Console
Classifier: License :: OSI Approved :: Apache Software License
Classifier: Programming Language :: Python :: 2.7
Classifier: Programming Language :: Python :: 3.3
Classifier: Programming Language :: Python :: 3.4
Classifier: Programming Language :: Python :: 3.5
Classifier: Programming Language :: Python :: 3.6
Classifier: Operating System :: POSIX :: Linux
Classifier: Topic :: Utilities
